MANIFEST.in
README.rst
setup.py
spvcm/__init__.py
spvcm/_constants.py
spvcm/abstracts.py
spvcm/api.py
spvcm/diagnostics.py
spvcm/ops.py
spvcm/plotting.py
spvcm/priors.py
spvcm/sqlite.py
spvcm/steps.py
spvcm/utils.py
spvcm/verify.py
spvcm.egg-info/PKG-INFO
spvcm.egg-info/SOURCES.txt
spvcm.egg-info/dependency_links.txt
spvcm.egg-info/not-zip-safe
spvcm.egg-info/requires.txt
spvcm.egg-info/top_level.txt
spvcm/both_levels/__init__.py
spvcm/both_levels/generic/__init__.py
spvcm/both_levels/generic/model.py
spvcm/both_levels/generic/sample.py
spvcm/both_levels/none/__init__.py
spvcm/both_levels/none/model.py
spvcm/both_levels/se_se/__init__.py
spvcm/both_levels/se_se/model.py
spvcm/both_levels/se_se/sample.py
spvcm/both_levels/se_sma/__init__.py
spvcm/both_levels/se_sma/model.py
spvcm/both_levels/sma_se/__init__.py
spvcm/both_levels/sma_se/model.py
spvcm/both_levels/sma_sma/__init__.py
spvcm/both_levels/sma_sma/model.py
spvcm/both_levels/tests/__init__.py
spvcm/both_levels/tests/make_data.py
spvcm/both_levels/tests/test_generic.py
spvcm/both_levels/tests/test_mvcm.py
spvcm/both_levels/tests/test_sese.py
spvcm/both_levels/tests/test_sesma.py
spvcm/both_levels/tests/test_smase.py
spvcm/both_levels/tests/test_smasma.py
spvcm/both_levels/tests/data/__init__.py
spvcm/both_levels/tests/data/generic.csv
spvcm/both_levels/tests/data/mvcm.csv
spvcm/both_levels/tests/data/sese.csv
spvcm/both_levels/tests/data/sesma.csv
spvcm/both_levels/tests/data/smase.csv
spvcm/both_levels/tests/data/smasma.csv
spvcm/custom_plots/__init__.py
spvcm/custom_plots/svcp.py
spvcm/examples/__init__.py
spvcm/examples/using_the_sampler.html
spvcm/examples/using_the_sampler.ipynb
spvcm/examples/__pycache__/__init__.cpython-37.pyc
spvcm/lower_level/__init__.py
spvcm/lower_level/se/__init__.py
spvcm/lower_level/se/model.py
spvcm/lower_level/sma/__init__.py
spvcm/lower_level/sma/model.py
spvcm/lower_level/tests/__init__.py
spvcm/lower_level/tests/make_data.py
spvcm/lower_level/tests/test_lower_se.py
spvcm/lower_level/tests/test_lower_sma.py
spvcm/lower_level/tests/data/lower_se.csv
spvcm/lower_level/tests/data/lower_sma.csv
spvcm/svc/__init__.py
spvcm/svc/model.py
