Metadata-Version: 1.0
Name: spvcm
Version: 0.3.0
Summary: Fit spatial multilevel models and diagnose convergence
Home-page: https://github.com/ljwolf/spvcm
Author: Levi John Wolf
Author-email: levi.john.wolf@gmail.com
License: 3-Clause BSD
Platform: UNKNOWN
